kbeta_pinn3d/__init__.py
kbeta_pinn3d/_shim.py
kbeta_pinn3d/pinn3d.py
kbeta_pinn3d/py.typed
kbeta_pinn3d/utils/plotting.py
kbeta_pinn3d/utils/visualization.py
kbeta_pinn3d-1.0.1.dist-info/licenses/LICENSE
kbeta_pinn3d-1.0.1.dist-info/METADATA
kbeta_pinn3d-1.0.1.dist-info/WHEEL
kbeta_pinn3d-1.0.1.dist-info/entry_points.txt
kbeta_pinn3d-1.0.1.dist-info/top_level.txt
kbeta_pinn3d-1.0.1.dist-info/RECORD
