Metadata-Version: 2.4
Name: kbeta_pinn3d
Version: 1.0.1
Summary: 3-D cylindrical PINN benchmark for the Kourkoutas-β optimizer paper
Author: Stavros Kassinos
License: MIT
Project-URL: Homepage, https://github.com/sck-at-ucy/kbeta-pinn3d
Project-URL: Documentation, https://github.com/sck-at-ucy/kbeta-pinn3d
Project-URL: Repository, https://github.com/sck-at-ucy/kbeta-pinn3d
Classifier: Programming Language :: Python :: 3
Classifier: Operating System :: MacOS :: MacOS X
Classifier: Intended Audience :: Science/Research
Classifier: Topic :: Scientific/Engineering :: Artificial Intelligence
Classifier: Topic :: Scientific/Engineering :: Physics
Requires-Python: >=3.11
License-File: LICENSE
Requires-Dist: mlx>=0.27.1
Requires-Dist: numpy>=2.3
Requires-Dist: matplotlib>=3.9
Requires-Dist: kbeta<2,>=1.0.0
Provides-Extra: dev
Requires-Dist: pytest; extra == "dev"
Requires-Dist: ruff; extra == "dev"
Requires-Dist: mypy; extra == "dev"
Requires-Dist: pre-commit; extra == "dev"
Requires-Dist: build; extra == "dev"
Requires-Dist: twine; extra == "dev"
Provides-Extra: viz
Requires-Dist: matplotlib>=3.9; extra == "viz"
Requires-Dist: seaborn>=0.13; extra == "viz"
Requires-Dist: pandas>=2.2; extra == "viz"
Provides-Extra: repro
Requires-Dist: mlx==0.26.3; extra == "repro"
Requires-Dist: kbeta==1.0.0; extra == "repro"
Requires-Dist: numpy==2.3.0; extra == "repro"
Requires-Dist: pyyaml; extra == "repro"
Requires-Dist: matplotlib>=3.9; extra == "repro"
Requires-Dist: seaborn>=0.13; extra == "repro"
Requires-Dist: pandas>=2.2; extra == "repro"
Requires-Dist: pytest; extra == "repro"
Requires-Dist: ruff; extra == "repro"
Requires-Dist: mypy; extra == "repro"
Dynamic: license-file
